flower_classifier/__init__.py
flower_classifier/configs/__init__.py
flower_classifier/configs/config.py
flower_classifier/dataload/__init__.py
flower_classifier/dataload/dataload.py
flower_classifier/dataload/download.py
flower_classifier/main.py
flower_classifier/model/__init__.py
flower_classifier/model/learner.py
flower_classifier/model/scheduler.py
flower_classifier/orchestrate.py
flower_classifier/references/references.md
flower_classifier/utils/__init__.py
flower_classifier/utils/logging.py
flower_classifier/utils/metrics.py
flower_classifier/utils/utils.py
flower_classifier-0.1.2.dist-info/LICENSE
flower_classifier-0.1.2.dist-info/WHEEL
flower_classifier-0.1.2.dist-info/METADATA
flower_classifier-0.1.2.dist-info/RECORD
